ai_agent/__init__.py
ai_agent/agent.py
ai_agent/entities.py
ai_agent/utils.py
ai_agent/version.py
ai_agent/core/__init__.py
ai_agent/core/core.py
ai_agent/core/abis/__init__.py
ai_agent/core/abis/agent.py
ai_agent/core/abis/manger.py
ai_agent/core/abis/proxy.py
attps/__init__.py
attps/version.py
attps/verify/__init__.py
attps/verify/agent.py
attps/verify/entities.py
attps/verify/core/__init__.py
attps/verify/core/core.py
attps/verify/core/abis/__init__.py
attps/verify/core/abis/agent.py
attps/verify/core/abis/manger.py
attps/verify/core/abis/proxy.py
tests/__init__.py
tests/test_agent.py
tests/test_attps_verify.py
utils/__init__.py
utils/utils.py
attps_sdk-1.1.0.dist-info/LICENSE
attps_sdk-1.1.0.dist-info/METADATA
attps_sdk-1.1.0.dist-info/WHEEL
attps_sdk-1.1.0.dist-info/top_level.txt
attps_sdk-1.1.0.dist-info/RECORD
