Metadata-Version: 2.1
Name: attps-sdk
Version: 1.1.0
Summary: ATTPs sdk for APRO
Home-page: https://github.com/APRO-com/ATTPs-sdk-python
Author: APRO
Author-email: apro@apro.com
Requires-Python: >=3.7, <4
License-File: LICENSE
Requires-Dist: web3 >7.0.0
Requires-Dist: python-dotenv >=1.0.1
Requires-Dist: pytest >=8.0.0
